aicmt/__init__.py
aicmt/__version__.py
aicmt/ai_analyzer.py
aicmt/cli.py
aicmt/cli_args.py
aicmt/cli_interface.py
aicmt/config.py
aicmt/git_operations.py
aicmt/utils.py
aicmt-0.1.4.dist-info/METADATA
aicmt-0.1.4.dist-info/WHEEL
aicmt-0.1.4.dist-info/entry_points.txt
aicmt-0.1.4.dist-info/licenses/LICENSE
aicmt-0.1.4.dist-info/RECORD
