Metadata-Version: 2.4
Name: aicmt
Version: 0.1.4
Summary: An intelligent Git commit assistant that not only generates commit messages, but also automatically analyzes and splits your code changes into multiple well-organized commits following best practices.
Project-URL: Homepage, https://github.com/versun/aicmt
Project-URL: Repository, https://github.com/versun/aicmt.git
Project-URL: Issues, https://github.com/versun/aicmt/issues
Author-email: Versun <aicmt@versun.me>
Maintainer-email: Versun <aicmt@versun.me>
License: MIT License
License-File: LICENSE
Keywords: ai,ai commit,ai git commit,aicmt,assistant,automated,change,code,commit,git,intelligence,intelligent,message
Requires-Python: >=3.10
Requires-Dist: gitpython
Requires-Dist: openai
Requires-Dist: rich
Provides-Extra: dev
Requires-Dist: pytest; extra == 'dev'
Requires-Dist: pytest-cov; extra == 'dev'
Requires-Dist: ruff; extra == 'dev'
